{"title": "庄子", "text": "鸿蒙曰：\"乱天之经，逆物之情，玄天弗成，解兽之群而鸟皆夜鸣，灾及草木，祸及止虫。意！治人之过也。\"云将曰：\"然则吾奈何？\"鸿蒙曰：\"意！毒哉！僊僊乎归矣！\"云将曰：\"吾遇天难，愿闻一言。\"鸿蒙曰：\"意！心养！汝徒处无为，而物自化。堕尔形体，吐尔聪明，伦与物忘，大同乎涬溟。解心释神，莫然无魂。万物云云，各复其根，各复其根而不知。浑浑沌沌，终身不离。若彼知之，乃是离之。无问其名，无窥其情，物固自生。\"云将曰：\"天降朕以德，示朕以默。躬身求之，乃今得也。\"再拜稽首，起辞而行。", "description": "世俗人都喜欢别人跟自己相同而讨厌别人跟自己不一样。希望别人跟自己相同，不希望别人跟自己不一样的人，总是把出人头地当作自己主要的内心追求。那些一心只想出人头地的人，何尝又能够真正超出众人呢！随顺众人之意当然能够得到安宁，可是个人的所闻总不如众人的技艺多才智高。希图治理邦国的人，必定是贪取夏、商、周三代帝王之利而又看不到这样做的后患的人。这样做是凭借统治国家的权力贪求个人的侥幸，而贪求个人的侥幸而不至于丧失国家统治权力的又有多少呢！他们中能够保存国家的，不到万分之一，而丧失国家的，自身一无所成而且还会留下许多祸患。可悲呀，拥有土地的统治者是何等的不聪明！", "book": "ZhuangZi", "total": 592, "current": 158, "next": "159.json", "prev": "157.json"}