{"title": "庄子", "text": "刻意尚行，离世异俗，高论怨诽，为亢而已矣。此山谷之士，非世之人，枯槁赴渊者之所好也。语仁义忠信，恭俭推让，为修而已矣。此平世之士，教诲之人，游居学者之所好也。语大功，立大名，礼君臣，正上下，为治而已矣。此朝廷之士，尊主强国之人，致功并兼者之所好也。就薮泽，处闲旷，钓鱼闲处，无为而已矣。此江海之士，避世之人，闲暇者之所好也。吹呴呼吸，吐故纳新，熊经鸟申，为寿而已矣。此道引之士，养形之人，彭祖寿考者之所好也。", "description": "“所以，礼义法度，都是顺应时代而有所变化的东西。如今捕捉到猿猴给它穿上周公的衣服，它必定会咬碎或撕裂，直到全部剥光身上的衣服方才心满意足。观察古今的差异，就象猿猴不同于周公。从前西施心口疼痛而皱着眉头在邻里间行走，邻里的一个丑女人看见了认为皱着眉头很美，回去后也在邻里间捂着胸口皱着眉头。邻里的有钱人看见了，紧闭家门而不出；贫穷的人看见了，带着妻儿子女远远地跑开了。那个丑女人只知道皱着眉头好看却不知道皱着眉头好看的原因。可惜呀，你的先生一定会遭遇厄运啊！”", "book": "ZhuangZi", "total": 592, "current": 228, "next": "229.json", "prev": "227.json"}