{"title": "庄子", "text": "缮性于俗学，以求复其初；滑欲于俗思，以求致其明：谓之蔽蒙之民。", "description": "老聃说：“年轻人，你再稍微靠前些！我对你说说三皇五帝治理天下的事。黄帝治理天下，使人民心地淳厚保持本真，百姓有谁死了双亲并不哭泣，人们也不会加以非议。唐尧治理天下，使百姓敬重双亲，百姓有谁为了敬重双亲依照等差而做到亲疏有别，人们同样也不会非议。虞舜治理天下，使百姓心存竞争，怀孕的妇女十个月生下孩子，孩子生下五个月就张口学话，不等长到两、三岁就开始识人问事，于是开始出现夭折短命的现象。夏禹治理天下，使百姓心怀变诈，人人存有机变之心因而动刀动枪成了理所当然之事，杀死盗贼不算杀人，人们各自结成团伙而肆意于天下，所以天下大受惊扰，儒家、墨家都纷纷而起。他们初始时也还有伦有理，可是时至今日以女为妇，还有什么可言呢！我告诉你。三皇五帝治理天下，名义上叫做治理，而扰乱人性和真情没有什么比他们更严重的了。三皇的心智就只是，对上而言遮掩了日月的光明，对下而言违背了山川的精粹，就中而言毁坏了四时的推移。他们的心智比蛇蝎之尾还惨毒，就连小小的兽类，也不可能使本性和真情获得安宁，可是还自以为是圣人。是不认为可耻吗，还是不知道可耻呢？”子贡听了惊惶不定，心神不安地站着。", "book": "ZhuangZi", "total": 592, "current": 237, "next": "238.json", "prev": "236.json"}