{"title": "庄子", "text": "南荣囗曰：\"然则是至人之德已乎？\"曰：\"非也。是乃所谓冰解冻释者。夫至人者，相与交食乎地而交乐乎天，不以人物利害相撄，不相与为怪，不相与为谋，不相与为事，翛然而往，侗然而来。是谓卫生之经已。\"曰：\"然则是至乎？\"曰：\"未也。吾固告汝曰：'能儿子乎！'儿子动不知所为，行不知所之，身若槁木之枝而心若死灰。若是者，祸亦不至，福亦不来。祸福无有，恶有人灾也！\"", "description": "庄子说：“先生的提问，本来就没有触及道的本质，一个名叫获的管理市场的官吏向屠夫询问猪的肥瘦，踩踏猪腿的部位越是往下就越能探知肥瘦的真实情况。你不要只是在某一事物里寻找道，万物没有什么东西可以逃离开它。‘至道’是这样，最伟大的言论也是这样。万物、言论和大道遍及各个角落，它们名称各异而实质却是相同，它们的意旨是归于同一的。让我们一道游历于什么也没有的地方，用混同合一的观点来加以讨论，宇宙万物的变化是没有穷尽的啊！我们再顺应变化无为而处吧！恬淡而又寂静啊！广漠而又清虚啊！调谐而又安闲啊！我的心思早已虚空宁寂，不会前往何处也不知道应该去到哪里，离去以后随即归来也从不知道停留的所在，我已在人世来来往往却并不了解哪里是最后的归宿；放纵我的思想遨游在虚旷的境域，大智的人跟大道交融相契而从不了解它的终极。造就万物的道跟万物本身并无界域之分，而事物之间的界线，就是所谓具体事物的差异；没有差异的区别，也就是表面存在差异而实质并非有什么区别。人们所说的盈满、空虚、衰退、减损，认为是盈满或空虚而并非真正是盈满或空虚，认为是衰退或减损而并非真正是衰退或减损，认为是宗本或末节而并非真正是宗本或末节，认为是积聚或离散而并非真正是积聚或离散。”", "book": "ZhuangZi", "total": 592, "current": 405, "next": "406.json", "prev": "404.json"}