{"title": "庄子", "text": "且子正为名，我正为利。名利之实，不顺于理，不监于道。吾日与子讼于无约，曰'小人殉财，君子殉名，其所以变其情、易其性则异矣；乃至于弃其所为而殉其所不为则一也。'故曰：无为小人，反殉而天；无为君子，从天之理。若枉若直，相而天极。面观四方，与时消息。若是若非，执而圆机。独成而意，与道徘徊。无转而行，无成而义，将失而所为。无赴而富，无殉而成，将弃而天。比干剖心，子胥抉眼，忠之祸也；直躬证父，尾生溺死，信之患也；鲍子立干，申子不自理，廉之害也；孔子不见母，匡子不见父，义之失也。此上世之所传、下世之所语以为士者，正其言，必其行，故服其殃、离其患也。\"", "description": "“而且你心里所想的正在于名，我心里所想的正为了利。名与利的实情，不合于理，也不明于道。我往日跟你在无约面前争论不休：‘小人为财而死，君子为名献身。然而他们变换真情、更改本性的原因，却没有不同；而竟至舍弃该做的事而不惜生命地追逐不该寻求的东西，那是同一样的。’所以说，不要去做小人，反过来追寻你自己的天性；不要去做君子，而顺从自然的规律。或曲或直，顺其自然；观察四方，跟随四时变化而消长。或是或非，牢牢掌握循环变化的中枢；独自完成你的心意，跟随大道往返进退。不要执着于你的德行，不要成就于你所说的规范；那将会丧失你的禀性。不要为了富有而劳苦奔波，不要为了成功而不惜献身，那将会舍弃自然的真性。比干被剖心，子胥被挖眼，这是忠的祸害；直躬出证父亲偷羊，尾生被水淹死，这是信的祸患；鲍焦抱树而立、干枯而死，申生宁可自缢也不申辩委屈，这是廉的毒害；孔子不能为母送终，匡子发誓不见父亲，这是义的过失。这些现象都是上世的传闻，当代的话题，总认为士大夫必定会让自己的言论正直，让自己的行动跟着去做，所以深受灾殃，遭逢如此的祸患。”", "book": "ZhuangZi", "total": 592, "current": 539, "next": "540.json", "prev": "538.json"}