{"title": "别房太尉墓", "text": "title:别房太尉墓\nauthor:杜甫\n他乡复行役，\n驻马别孤坟。\n近泪无干土，\n低空有断云。\n 对棋陪谢傅，\n把剑觅徐君。\n唯见林花落，\n莺啼送客闻。\n", "description": "##翻译\n我东西漂泊，一再奔走他乡异土，今日歇脚阆州，来悼别你的孤坟。泪水沾湿了泥土，心情十分悲痛，精神恍惚，就象低空飘飞的断云。当年与你对棋，比你为晋朝谢安，而今在你墓前，象季札拜别徐君。不堪回首，眼前只见这林花错落，离去时，听得黄莺啼声凄怆难闻。\n##赏析\n<strong>分句分析</strong><br>\n\n“他乡复行役，驻马别孤坟。”既在他乡复值行役之中，公事在身，行色匆匆。尽管如此，诗\n\n诗人表达的感情十分深沉而含蓄，这是因为房琯的问题，事干政局，诗人已经为此吃了苦头，自有难言之苦。但诗中那阴郁的氛围，那深沉的哀痛，还是表现出诗人不只是悼念亡友而已，更多的是内心对国事的殷忧和叹息。\n##背景\n<strong>分句分析</strong><br>\n\n“他乡复行役，驻马别孤坟。”既在他乡复值行役之中，公事在身，行色匆匆。尽管如此，诗\n\n诗人表达的感情十分深沉而含蓄，这是因为房琯的问题，事干政局，诗人已经为此吃了苦头，自有难言之苦。但诗中那阴郁的氛围，那深沉的哀痛，还是表现出诗人不只是悼念亡友而已，更多的是内心对国事的殷忧和叹息。", "book": "TangShi", "total": 320, "current": 111, "next": "112.json", "prev": "110.json"}