{"title": "登金陵凤凰台", "text": "title:登金陵凤凰台\nauthor:李白\n凤凰台上凤凰游，凤去台空江自流。\n吴宫花草埋幽径，晋代衣冠成古丘。\n三山半落青天外，二水中分白鹭洲。\n总为浮云能蔽日，长安不见使人愁。\n", "is_formate_text": true, "description": "##翻译\n凤凰台上曾经有凤凰来悠游，凤去台空只有江水依旧东流。吴宫鲜花芳草埋着荒凉小径，晋代多少王族已成荒冢古丘。三山云雾中隐现如落青天外，江水被白鹭洲分成两条河流。总有奸臣当道犹如浮云遮日，长安望不见心中郁闷长怀愁。\n##赏析\n《登金陵凤凰台》是唐代的律诗李白此诗的艺术特点，又在于对时空观念的完美表达。这既体现在对历史与自然的认识上，也体现在他构造时空艺术境界的表达方法上。李白强调的自然永恒不朽，一方面是宣传他的以自然为中心的“物我为一”的世界观，另一方面也是为了揭露历史上的统治神话。因为从古而来，几乎所有的统治者他们都宣扬自己的世代永存与精神不灭，并且还把这样一种模式灌输到人们的意识形态当中，使人深信不疑。但是，李白则对此不以为然。他认为即或是极为强有力的统治者，就像秦始皇，他可以“挥剑决浮云，诸侯尽西来。明断自天启，大略驾群才”，然而他终归也要“但见三泉下，金棺葬寒灰”（《古风·秦王扫六合》），烟消云散是不可避免的。所以，在李白看来，宇宙万物之中，能够获得永恒存在的只有自然。一切的繁华与骄奢淫逸都会烟消云散；如果说它们还存在，似乎也只是作为自然的反衬而存在的。另外，李白在表现自然力量的雄大与变化的时空观时，则选取了最为典型的事物，即“三山半落”之混茫与“二水中分”之辽阔，从而构造出阔大的境界，并且把历史的变迁，即时间的改变与地点的依旧，即空间的不改整体地表现出来，启发人们作更深的思考。\n\n李白《登金陵凤凰台》的艺术特点，还在于别致自然的遣词造句。由于诗以寓目山河为线索，于是追求情随景生，意象谐成也就显得特别重要。“凤凰”的高飞与“凤凰台”的“空”，洁净、疏朗，与诗人潇洒的气质和略带感伤的情怀相一致，且意到笔到，词义契合，起到了内外呼应的作用。另外，整首“登临”的内在精神，与“埋幽径”“成古丘”的冷落清凉，与“三山”“二水”的自然境界，与忧谗畏讥的“浮云”惆怅和不见“长安”无奈凄凉，都被恰切的语词链条紧紧地钩连在一起，从而当得起“古今题咏，惟谪仙为绝唱”的赞誉。\n##背景\n《登金陵凤凰台》是李白集中为数不多的七言律诗之一。此诗一说是天宝（唐玄宗年号，742～756）年间，作者奉命“赐金还山”，被排挤离开长安，南游金陵时所作；一说是作者流放夜郎遇赦返回后所作；也有人称是李白游览黄鹤楼，并留下“眼前有景道不得，崔颢题诗在上头”后写的，是想与崔颢的《黄鹤楼》争胜。", "book": "TangShi", "total": 320, "current": 170, "next": "171.json", "prev": "169.json"}